{
  "last_archive": "JORF_20260722-002953.tar.gz",
  "decrees": [
    {
      "jorftext_id": "JORFTEXT000054424111",
      "jo_date": "14 juillet 2026",
      "decret_date": "9 juillet 2026",
      "jo_date_iso": "2026-07-14",
      "decret_date_iso": "2026-07-09",
      "url": "https://www.legifrance.gouv.fr/jorf/id/JORFTEXT000054424111"
    },
    {
      "jorftext_id": "JORFTEXT000054424108",
      "jo_date": "14 juillet 2026",
      "decret_date": "7 juillet 2026",
      "jo_date_iso": "2026-07-14",
      "decret_date_iso": "2026-07-07",
      "url": "https://www.legifrance.gouv.fr/jorf/id/JORFTEXT000054424108"
    },
    {
      "jorftext_id": "JORFTEXT000054399923",
      "jo_date": "9 juillet 2026",
      "decret_date": "7 juillet 2026",
      "jo_date_iso": "2026-07-09",
      "decret_date_iso": "2026-07-07",
      "url": "https://www.legifrance.gouv.fr/jorf/id/JORFTEXT000054399923"
    },
    {
      "jorftext_id": "JORFTEXT000054399920",
      "jo_date": "9 juillet 2026",
      "decret_date": "6 juillet 2026",
      "jo_date_iso": "2026-07-09",
      "decret_date_iso": "2026-07-06",
      "url": "https://www.legifrance.gouv.fr/jorf/id/JORFTEXT000054399920"
    },
    {
      "jorftext_id": "JORFTEXT000054387081",
      "jo_date": "4 juillet 2026",
      "decret_date": "30 juin 2026",
      "jo_date_iso": "2026-07-04",
      "decret_date_iso": "2026-06-30",
      "url": "https://www.legifrance.gouv.fr/jorf/id/JORFTEXT000054387081"
    },
    {
      "jorftext_id": "JORFTEXT000054387078",
      "jo_date": "4 juillet 2026",
      "decret_date": "30 juin 2026",
      "jo_date_iso": "2026-07-04",
      "decret_date_iso": "2026-06-30",
      "url": "https://www.legifrance.gouv.fr/jorf/id/JORFTEXT000054387078"
    },
    {
      "jorftext_id": "JORFTEXT000054281665",
      "jo_date": "20 juin 2026",
      "decret_date": "18 juin 2026",
      "jo_date_iso": "2026-06-20",
      "decret_date_iso": "2026-06-18",
      "url": "https://www.legifrance.gouv.fr/jorf/id/JORFTEXT000054281665"
    },
    {
      "jorftext_id": "JORFTEXT000054281659",
      "jo_date": "20 juin 2026",
      "decret_date": "17 juin 2026",
      "jo_date_iso": "2026-06-20",
      "decret_date_iso": "2026-06-17",
      "url": "https://www.legifrance.gouv.fr/jorf/id/JORFTEXT000054281659"
    },
    {
      "jorftext_id": "JORFTEXT000054200946",
      "jo_date": "5 juin 2026",
      "decret_date": "1er juin 2026",
      "jo_date_iso": "2026-06-05",
      "decret_date_iso": "2026-06-01",
      "url": "https://www.legifrance.gouv.fr/jorf/id/JORFTEXT000054200946"
    },
    {
      "jorftext_id": "JORFTEXT000054200943",
      "jo_date": "5 juin 2026",
      "decret_date": "1er juin 2026",
      "jo_date_iso": "2026-06-05",
      "decret_date_iso": "2026-06-01",
      "url": "https://www.legifrance.gouv.fr/jorf/id/JORFTEXT000054200943"
    },
    {
      "jorftext_id": "JORFTEXT000054113932",
      "jo_date": "20 mai 2026",
      "decret_date": "15 mai 2026",
      "jo_date_iso": "2026-05-20",
      "decret_date_iso": "2026-05-15",
      "url": "https://www.legifrance.gouv.fr/jorf/id/JORFTEXT000054113932"
    },
    {
      "jorftext_id": "JORFTEXT000054101491",
      "jo_date": "14 mai 2026",
      "decret_date": "12 mai 2026",
      "jo_date_iso": "2026-05-14",
      "decret_date_iso": "2026-05-12",
      "url": "https://www.legifrance.gouv.fr/jorf/id/JORFTEXT000054101491"
    },
    {
      "jorftext_id": "JORFTEXT000054101488",
      "jo_date": "14 mai 2026",
      "decret_date": "11 mai 2026",
      "jo_date_iso": "2026-05-14",
      "decret_date_iso": "2026-05-11",
      "url": "https://www.legifrance.gouv.fr/jorf/id/JORFTEXT000054101488"
    },
    {
      "jorftext_id": "JORFTEXT000054101485",
      "jo_date": "14 mai 2026",
      "decret_date": "7 mai 2026",
      "jo_date_iso": "2026-05-14",
      "decret_date_iso": "2026-05-07",
      "url": "https://www.legifrance.gouv.fr/jorf/id/JORFTEXT000054101485"
    },
    {
      "jorftext_id": "JORFTEXT000053959056",
      "jo_date": "26 avril 2026",
      "decret_date": "14 avril 2026",
      "jo_date_iso": "2026-04-26",
      "decret_date_iso": "2026-04-14",
      "url": "https://www.legifrance.gouv.fr/jorf/id/JORFTEXT000053959056"
    },
    {
      "jorftext_id": "JORFTEXT000053796559",
      "jo_date": "11 avril 2026",
      "decret_date": "8 avril 2026",
      "jo_date_iso": "2026-04-11",
      "decret_date_iso": "2026-04-08",
      "url": "https://www.legifrance.gouv.fr/jorf/id/JORFTEXT000053796559"
    },
    {
      "jorftext_id": "JORFTEXT000053764262",
      "jo_date": "5 avril 2026",
      "decret_date": "1er avril 2026",
      "jo_date_iso": "2026-04-05",
      "decret_date_iso": "2026-04-01",
      "url": "https://www.legifrance.gouv.fr/jorf/id/JORFTEXT000053764262"
    },
    {
      "jorftext_id": "JORFTEXT000053727557",
      "jo_date": "28 mars 2026",
      "decret_date": "23 mars 2026",
      "jo_date_iso": "2026-03-28",
      "decret_date_iso": "2026-03-23",
      "url": "https://www.legifrance.gouv.fr/jorf/id/JORFTEXT000053727557"
    },
    {
      "jorftext_id": "JORFTEXT000053708326",
      "jo_date": "22 mars 2026",
      "decret_date": "19 mars 2026",
      "jo_date_iso": "2026-03-22",
      "decret_date_iso": "2026-03-19",
      "url": "https://www.legifrance.gouv.fr/jorf/id/JORFTEXT000053708326"
    },
    {
      "jorftext_id": "JORFTEXT000053672008",
      "jo_date": "15 mars 2026",
      "decret_date": "4 mars 2026",
      "jo_date_iso": "2026-03-15",
      "decret_date_iso": "2026-03-04",
      "url": "https://www.legifrance.gouv.fr/jorf/id/JORFTEXT000053672008"
    },
    {
      "jorftext_id": "JORFTEXT000053669568",
      "jo_date": "14 mars 2026",
      "decret_date": "10 mars 2026",
      "jo_date_iso": "2026-03-14",
      "decret_date_iso": "2026-03-10",
      "url": "https://www.legifrance.gouv.fr/jorf/id/JORFTEXT000053669568"
    },
    {
      "jorftext_id": "JORFTEXT000053510656",
      "jo_date": "20 février 2026",
      "decret_date": "17 février 2026",
      "jo_date_iso": "2026-02-20",
      "decret_date_iso": "2026-02-17",
      "url": "https://www.legifrance.gouv.fr/jorf/id/JORFTEXT000053510656"
    },
    {
      "jorftext_id": "JORFTEXT000053484488",
      "jo_date": "15 février 2026",
      "decret_date": "13 février 2026",
      "jo_date_iso": "2026-02-15",
      "decret_date_iso": "2026-02-13",
      "url": "https://www.legifrance.gouv.fr/jorf/id/JORFTEXT000053484488"
    },
    {
      "jorftext_id": "JORFTEXT000053466028",
      "jo_date": "13 février 2026",
      "decret_date": "11 février 2026",
      "jo_date_iso": "2026-02-13",
      "decret_date_iso": "2026-02-11",
      "url": "https://www.legifrance.gouv.fr/jorf/id/JORFTEXT000053466028"
    },
    {
      "jorftext_id": "JORFTEXT000053444324",
      "jo_date": "6 février 2026",
      "decret_date": "5 février 2026",
      "jo_date_iso": "2026-02-06",
      "decret_date_iso": "2026-02-05",
      "url": "https://www.legifrance.gouv.fr/jorf/id/JORFTEXT000053444324"
    },
    {
      "jorftext_id": "JORFTEXT000053444318",
      "jo_date": "6 février 2026",
      "decret_date": "4 février 2026",
      "jo_date_iso": "2026-02-06",
      "decret_date_iso": "2026-02-04",
      "url": "https://www.legifrance.gouv.fr/jorf/id/JORFTEXT000053444318"
    },
    {
      "jorftext_id": "JORFTEXT000053396073",
      "jo_date": "23 janvier 2026",
      "decret_date": "21 janvier 2026",
      "jo_date_iso": "2026-01-23",
      "decret_date_iso": "2026-01-21",
      "url": "https://www.legifrance.gouv.fr/jorf/id/JORFTEXT000053396073"
    },
    {
      "jorftext_id": "JORFTEXT000053175492",
      "jo_date": "27 décembre 2025",
      "decret_date": "26 décembre 2025",
      "jo_date_iso": "2025-12-27",
      "decret_date_iso": "2025-12-26",
      "url": "https://www.legifrance.gouv.fr/jorf/id/JORFTEXT000053175492"
    },
    {
      "jorftext_id": "JORFTEXT000052995524",
      "jo_date": "7 décembre 2025",
      "decret_date": "5 décembre 2025",
      "jo_date_iso": "2025-12-07",
      "decret_date_iso": "2025-12-05",
      "url": "https://www.legifrance.gouv.fr/jorf/id/JORFTEXT000052995524"
    },
    {
      "jorftext_id": "JORFTEXT000052953616",
      "jo_date": "30 novembre 2025",
      "decret_date": "28 novembre 2025",
      "jo_date_iso": "2025-11-30",
      "decret_date_iso": "2025-11-28",
      "url": "https://www.legifrance.gouv.fr/jorf/id/JORFTEXT000052953616"
    },
    {
      "jorftext_id": "JORFTEXT000052556399",
      "jo_date": "11 novembre 2025",
      "decret_date": "7 novembre 2025",
      "jo_date_iso": "2025-11-11",
      "decret_date_iso": "2025-11-07",
      "url": "https://www.legifrance.gouv.fr/jorf/id/JORFTEXT000052556399"
    },
    {
      "jorftext_id": "JORFTEXT000052474689",
      "jo_date": "1er novembre 2025",
      "decret_date": "31 octobre 2025",
      "jo_date_iso": "2025-11-01",
      "decret_date_iso": "2025-10-31",
      "url": "https://www.legifrance.gouv.fr/jorf/id/JORFTEXT000052474689"
    },
    {
      "jorftext_id": "JORFTEXT000052381147",
      "jo_date": "11 octobre 2025",
      "decret_date": "10 octobre 2025",
      "jo_date_iso": "2025-10-11",
      "decret_date_iso": "2025-10-10",
      "url": "https://www.legifrance.gouv.fr/jorf/id/JORFTEXT000052381147"
    },
    {
      "jorftext_id": "JORFTEXT000052260674",
      "jo_date": "19 septembre 2025",
      "decret_date": "18 septembre 2025",
      "jo_date_iso": "2025-09-19",
      "decret_date_iso": "2025-09-18",
      "url": "https://www.legifrance.gouv.fr/jorf/id/JORFTEXT000052260674"
    },
    {
      "jorftext_id": "JORFTEXT000052178305",
      "jo_date": "2 septembre 2025",
      "decret_date": "1er septembre 2025",
      "jo_date_iso": "2025-09-02",
      "decret_date_iso": "2025-09-01",
      "url": "https://www.legifrance.gouv.fr/jorf/id/JORFTEXT000052178305"
    },
    {
      "jorftext_id": "JORFTEXT000052050726",
      "jo_date": "6 août 2025",
      "decret_date": "4 août 2025",
      "jo_date_iso": "2025-08-06",
      "decret_date_iso": "2025-08-04",
      "url": "https://www.legifrance.gouv.fr/jorf/id/JORFTEXT000052050726"
    },
    {
      "jorftext_id": "JORFTEXT000051832872",
      "jo_date": "2 juillet 2025",
      "decret_date": "1er juillet 2025",
      "jo_date_iso": "2025-07-02",
      "decret_date_iso": "2025-07-01",
      "url": "https://www.legifrance.gouv.fr/jorf/id/JORFTEXT000051832872"
    },
    {
      "jorftext_id": "JORFTEXT000051796655",
      "jo_date": "26 juin 2025",
      "decret_date": "24 juin 2025",
      "jo_date_iso": "2025-06-26",
      "decret_date_iso": "2025-06-24",
      "url": "https://www.legifrance.gouv.fr/jorf/id/JORFTEXT000051796655"
    },
    {
      "jorftext_id": "JORFTEXT000051690470",
      "jo_date": "5 juin 2025",
      "decret_date": "3 juin 2025",
      "jo_date_iso": "2025-06-05",
      "decret_date_iso": "2025-06-03",
      "url": "https://www.legifrance.gouv.fr/jorf/id/JORFTEXT000051690470"
    },
    {
      "jorftext_id": "JORFTEXT000051587204",
      "jo_date": "14 mai 2025",
      "decret_date": "12 mai 2025",
      "jo_date_iso": "2025-05-14",
      "decret_date_iso": "2025-05-12",
      "url": "https://www.legifrance.gouv.fr/jorf/id/JORFTEXT000051587204"
    },
    {
      "jorftext_id": "JORFTEXT000051550985",
      "jo_date": "4 mai 2025",
      "decret_date": "2 mai 2025",
      "jo_date_iso": "2025-05-04",
      "decret_date_iso": "2025-05-02",
      "url": "https://www.legifrance.gouv.fr/jorf/id/JORFTEXT000051550985"
    },
    {
      "jorftext_id": "JORFTEXT000051445383",
      "jo_date": "10 avril 2025",
      "decret_date": "8 avril 2025",
      "jo_date_iso": "2025-04-10",
      "decret_date_iso": "2025-04-08",
      "url": "https://www.legifrance.gouv.fr/jorf/id/JORFTEXT000051445383"
    },
    {
      "jorftext_id": "JORFTEXT000051305077",
      "jo_date": "8 mars 2025",
      "decret_date": "7 mars 2025",
      "jo_date_iso": "2025-03-08",
      "decret_date_iso": "2025-03-07",
      "url": "https://www.legifrance.gouv.fr/jorf/id/JORFTEXT000051305077"
    },
    {
      "jorftext_id": "JORFTEXT000051145177",
      "jo_date": "8 février 2025",
      "decret_date": "5 février 2025",
      "jo_date_iso": "2025-02-08",
      "decret_date_iso": "2025-02-05",
      "url": "https://www.legifrance.gouv.fr/jorf/id/JORFTEXT000051145177"
    },
    {
      "jorftext_id": "JORFTEXT000051108230",
      "jo_date": "2 février 2025",
      "decret_date": "31 janvier 2025",
      "jo_date_iso": "2025-02-02",
      "decret_date_iso": "2025-01-31",
      "url": "https://www.legifrance.gouv.fr/jorf/id/JORFTEXT000051108230"
    },
    {
      "jorftext_id": "JORFTEXT000050998788",
      "jo_date": "18 janvier 2025",
      "decret_date": "17 janvier 2025",
      "jo_date_iso": "2025-01-18",
      "decret_date_iso": "2025-01-17",
      "url": "https://www.legifrance.gouv.fr/jorf/id/JORFTEXT000050998788"
    },
    {
      "jorftext_id": "JORFTEXT000050976832",
      "jo_date": "15 janvier 2025",
      "decret_date": "14 janvier 2025",
      "jo_date_iso": "2025-01-15",
      "decret_date_iso": "2025-01-14",
      "url": "https://www.legifrance.gouv.fr/jorf/id/JORFTEXT000050976832"
    },
    {
      "jorftext_id": "JORFTEXT000050950029",
      "jo_date": "5 janvier 2025",
      "decret_date": "3 janvier 2025",
      "jo_date_iso": "2025-01-05",
      "decret_date_iso": "2025-01-03",
      "url": "https://www.legifrance.gouv.fr/jorf/id/JORFTEXT000050950029"
    },
    {
      "jorftext_id": "JORFTEXT000050874306",
      "jo_date": "31 décembre 2024",
      "decret_date": "27 décembre 2024",
      "jo_date_iso": "2024-12-31",
      "decret_date_iso": "2024-12-27",
      "url": "https://www.legifrance.gouv.fr/jorf/id/JORFTEXT000050874306"
    },
    {
      "jorftext_id": "JORFTEXT000050663982",
      "jo_date": "27 novembre 2024",
      "decret_date": "26 novembre 2024",
      "jo_date_iso": "2024-11-27",
      "decret_date_iso": "2024-11-26",
      "url": "https://www.legifrance.gouv.fr/jorf/id/JORFTEXT000050663982"
    },
    {
      "jorftext_id": "JORFTEXT000050407591",
      "jo_date": "30 octobre 2024",
      "decret_date": "28 octobre 2024",
      "jo_date_iso": "2024-10-30",
      "decret_date_iso": "2024-10-28",
      "url": "https://www.legifrance.gouv.fr/jorf/id/JORFTEXT000050407591"
    },
    {
      "jorftext_id": "JORFTEXT000050295286",
      "jo_date": "2 octobre 2024",
      "decret_date": "30 septembre 2024",
      "jo_date_iso": "2024-10-02",
      "decret_date_iso": "2024-09-30",
      "url": "https://www.legifrance.gouv.fr/jorf/id/JORFTEXT000050295286"
    },
    {
      "jorftext_id": "JORFTEXT000050179470",
      "jo_date": "5 septembre 2024",
      "decret_date": "4 septembre 2024",
      "jo_date_iso": "2024-09-05",
      "decret_date_iso": "2024-09-04",
      "url": "https://www.legifrance.gouv.fr/jorf/id/JORFTEXT000050179470"
    },
    {
      "jorftext_id": "JORFTEXT000050081275",
      "jo_date": "8 août 2024",
      "decret_date": "6 août 2024",
      "jo_date_iso": "2024-08-08",
      "decret_date_iso": "2024-08-06",
      "url": "https://www.legifrance.gouv.fr/jorf/id/JORFTEXT000050081275"
    },
    {
      "jorftext_id": "JORFTEXT000050052754",
      "jo_date": "26 juillet 2024",
      "decret_date": "24 juillet 2024",
      "jo_date_iso": "2024-07-26",
      "decret_date_iso": "2024-07-24",
      "url": "https://www.legifrance.gouv.fr/jorf/id/JORFTEXT000050052754"
    },
    {
      "jorftext_id": "JORFTEXT000049748640",
      "jo_date": "20 juin 2024",
      "decret_date": "18 juin 2024",
      "jo_date_iso": "2024-06-20",
      "decret_date_iso": "2024-06-18",
      "url": "https://www.legifrance.gouv.fr/jorf/id/JORFTEXT000049748640"
    },
    {
      "jorftext_id": "JORFTEXT000049503863",
      "jo_date": "5 mai 2024",
      "decret_date": "3 mai 2024",
      "jo_date_iso": "2024-05-05",
      "decret_date_iso": "2024-05-03",
      "url": "https://www.legifrance.gouv.fr/jorf/id/JORFTEXT000049503863"
    },
    {
      "jorftext_id": "JORFTEXT000049364854",
      "jo_date": "4 avril 2024",
      "decret_date": "3 avril 2024",
      "jo_date_iso": "2024-04-04",
      "decret_date_iso": "2024-04-03",
      "url": "https://www.legifrance.gouv.fr/jorf/id/JORFTEXT000049364854"
    },
    {
      "jorftext_id": "JORFTEXT000049285992",
      "jo_date": "16 mars 2024",
      "decret_date": "14 mars 2024",
      "jo_date_iso": "2024-03-16",
      "decret_date_iso": "2024-03-14",
      "url": "https://www.legifrance.gouv.fr/jorf/id/JORFTEXT000049285992"
    },
    {
      "jorftext_id": "JORFTEXT000049137145",
      "jo_date": "14 février 2024",
      "decret_date": "12 février 2024",
      "jo_date_iso": "2024-02-14",
      "decret_date_iso": "2024-02-12",
      "url": "https://www.legifrance.gouv.fr/jorf/id/JORFTEXT000049137145"
    },
    {
      "jorftext_id": "JORFTEXT000048815602",
      "jo_date": "4 janvier 2024",
      "decret_date": "2 janvier 2024",
      "jo_date_iso": "2024-01-04",
      "decret_date_iso": "2024-01-02",
      "url": "https://www.legifrance.gouv.fr/jorf/id/JORFTEXT000048815602"
    }
  ],
  "content_date": "2026-07-14"
}